tranqu/__init__.py
tranqu/device_type_manager.py
tranqu/program_type_manager.py
tranqu/tranqu.py
tranqu/tranqu_error.py
tranqu/transpile_result.py
tranqu/transpiler_dispatcher.py
tranqu/device_converter/__init__.py
tranqu/device_converter/device_converter.py
tranqu/device_converter/device_converter_manager.py
tranqu/device_converter/oqtopus_to_ouqu_tp_device_converter.py
tranqu/device_converter/oqtopus_to_qiskit_device_converter.py
tranqu/device_converter/pass_through_device_converter.py
tranqu/device_converter/qiskit_device.py
tranqu/device_converter/qiskit_to_ouqu_tp_device_converter.py
tranqu/program_converter/__init__.py
tranqu/program_converter/openqasm3_to_qiskit_program_converter.py
tranqu/program_converter/openqasm3_to_tket_program_converter.py
tranqu/program_converter/pass_through_program_converter.py
tranqu/program_converter/program_converter.py
tranqu/program_converter/program_converter_manager.py
tranqu/program_converter/qiskit_to_openqasm3_program_converter.py
tranqu/program_converter/qiskit_to_tket_program_converter.py
tranqu/program_converter/tket_to_openqasm3_program_converter.py
tranqu/program_converter/tket_to_qiskit_program_converter.py
tranqu/transpiler/__init__.py
tranqu/transpiler/ouqu_tp_transpiler.py
tranqu/transpiler/qiskit_layout_mapper.py
tranqu/transpiler/qiskit_stats_extractor.py
tranqu/transpiler/qiskit_transpiler.py
tranqu/transpiler/transpiler.py
tranqu/transpiler/transpiler_manager.py
tranqu-1.0.0.dist-info/METADATA
tranqu-1.0.0.dist-info/WHEEL
tranqu-1.0.0.dist-info/licenses/LICENSE
tranqu-1.0.0.dist-info/RECORD
