Metadata-Version: 2.4
Name: tranqu
Version: 1.0.0
Summary: Tranqu: A one-stop framework for transpilers across multiple quantum programming libraries and formats for quantum circuits
Project-URL: documentation, https://tranqu.readthedocs.io/
Project-URL: repository, https://github.com/oqtopus-team/tranqu
Author-email: oqtopus-team <oqtopus-team@googlegroups.com>
License-Expression: Apache-2.0
License-File: LICENSE
Classifier: Development Status :: 4 - Beta
Classifier: Intended Audience :: Developers
Classifier: Intended Audience :: Science/Research
Classifier: License :: OSI Approved :: Apache Software License
Classifier: Programming Language :: Python
Classifier: Programming Language :: Python :: 3.10
Classifier: Programming Language :: Python :: 3.11
Classifier: Programming Language :: Python :: 3.12
Classifier: Programming Language :: Python :: Implementation :: CPython
Classifier: Programming Language :: Python :: Implementation :: PyPy
Classifier: Topic :: Scientific/Engineering
Classifier: Topic :: Scientific/Engineering :: Physics
Requires-Python: >=3.10
Requires-Dist: ouqu-tp>=1.0.3
Requires-Dist: pytket-qiskit>=0.56.0
Requires-Dist: pytket<2.0.0,>=1.33.0
Requires-Dist: qiskit-qasm3-import>=0.5.0
Requires-Dist: qiskit<=1.4.0,>=1.0.0
